Metadata-Version: 2.4
Name: lgatr
Version: 1.4.2
Summary: Lorentz-Equivariant Geometric Algebra Transformer for High-Energy Physics
Author-email: Jonas Spinner <j.spinner@thphys.uni-heidelberg.de>, Víctor Bresó <breso@thphys.uni-heidelberg.de>
Project-URL: homepage, https://heidelberg-hepml.github.io/lgatr
Project-URL: repository, https://github.com/heidelberg-hepml/lgatr
Requires-Python: >=3.10
License-File: LICENSE
Requires-Dist: torch>=2.0
Requires-Dist: numpy
Requires-Dist: einops
Requires-Dist: opt_einsum
Provides-Extra: xformers-attention
Requires-Dist: xformers; extra == "xformers-attention"
Provides-Extra: flex-attention
Requires-Dist: torch>=2.7; extra == "flex-attention"
Provides-Extra: flash-attention
Requires-Dist: flash-attn; extra == "flash-attention"
Provides-Extra: dev
Requires-Dist: pytest; extra == "dev"
Requires-Dist: pytest-cov; extra == "dev"
Requires-Dist: clifford>=1.5.0; extra == "dev"
Requires-Dist: lloca; extra == "dev"
Requires-Dist: sphinx<9.0; extra == "dev"
Requires-Dist: sphinx-autodoc-typehints; extra == "dev"
Requires-Dist: sphinx-rtd-theme; extra == "dev"
Dynamic: license-file
